selenium_session_client/session_client.py
selenium_session_client-1.0.3.dist-info/LICENSE.txt
selenium_session_client-1.0.3.dist-info/METADATA
selenium_session_client-1.0.3.dist-info/WHEEL
selenium_session_client-1.0.3.dist-info/top_level.txt
selenium_session_client-1.0.3.dist-info/RECORD
