Metadata-Version: 2.1
Name: selenium-session-client
Version: 1.0.3
Summary: Bypass your app login screen by managing your browser session (cookies)
Home-page: https://github.com/blinq-io/selenium-session-manager
Author: dev0-blinq
Author-email: dev@blinq.io
License: MIT
Project-URL: Documentation, https://github.com/blinq-io/selenium-session-manager
Platform: any
Classifier: Programming Language :: Python
License-File: LICENSE.txt
Requires-Dist: requests
Requires-Dist: selenium
Requires-Dist: importlib-metadata ; python_version < "3.8"
Provides-Extra: testing
Requires-Dist: setuptools ; extra == 'testing'
Requires-Dist: pytest ; extra == 'testing'
Requires-Dist: pytest-cov ; extra == 'testing'
